werr-0.3.0.dist-info/licenses/LICENSE
werrlib/__init__.py
werrlib/cli.py
werrlib/cmd.py
werrlib/config.py
werrlib/main.py
werrlib/report.py
werrlib/task.py
werrlib/xml.py
werr-0.3.0.dist-info/.gitignore
werr-0.3.0.dist-info/METADATA
werr-0.3.0.dist-info/WHEEL
werr-0.3.0.dist-info/entry_points.txt
werr-0.3.0.dist-info/top_level.txt
werr-0.3.0.dist-info/RECORD
