Metadata-Version: 2.4
Name: werr
Version: 0.3.0
Summary: A python project task runner
Project-URL: Homepage, https://github.com/jhjn/werr
Project-URL: Repository, https://github.com/jhjn/werr
Keywords: tasks,task-runner,makefile,checks,uv,automation,werr
Classifier: Environment :: Console
Classifier: Intended Audience :: Developers
Classifier: License :: OSI Approved :: MIT License
Classifier: Operating System :: OS Independent
Classifier: Programming Language :: Python :: 3 :: Only
Classifier: Programming Language :: Python :: 3.14
Classifier: Programming Language :: Python
Classifier: Topic :: Software Development :: Build Tools
Classifier: Topic :: Software Development :: Quality Assurance
Classifier: Topic :: Software Development :: Testing
Requires-Python: >=3.14
License-File: LICENSE
Dynamic: license-file
